Metadata-Version: 1.1
Name: invenio-trends
Version: 1.0.0a1
Summary: Invenio module that adds a trends api to the platform.
Home-page: https://github.com/inspirehep/invenio-trends
Author: CERN
Author-email: teo.stocco@cern.ch
License: GPLv2
Keywords: invenio,trends,analysis,elasticsearch,ngrams
Platform: any
Classifier: Environment :: Web Environment
Classifier: Intended Audience :: Developers
Classifier: License :: OSI Approved :: GNU General Public License v2 (GPLv2)
Classifier: Operating System :: OS Independent
Classifier: Programming Language :: Python
Classifier: Topic :: Internet :: WWW/HTTP :: Dynamic Content
Classifier: Topic :: Software Development :: Libraries :: Python Modules
Classifier: Programming Language :: Python :: 2
Classifier: Programming Language :: Python :: 2.7
Classifier: Programming Language :: Python :: 3
Classifier: Programming Language :: Python :: 3.3
Classifier: Programming Language :: Python :: 3.4
Classifier: Programming Language :: Python :: 3.5
Classifier: Development Status :: 1 - Planning
